diamondback/__init__.py
diamondback/commons/__init__.py
diamondback/commons/log.py
diamondback/commons/rest_client.py
diamondback/commons/serial.py
diamondback/filters/__init__.py
diamondback/filters/complex_bandpass_filter.py
diamondback/filters/complex_exponential_filter.py
diamondback/filters/complex_frequency_filter.py
diamondback/filters/derivative_filter.py
diamondback/filters/fir_filter.py
diamondback/filters/goertzel_filter.py
diamondback/filters/iir_filter.py
diamondback/filters/integral_filter.py
diamondback/filters/pid_filter.py
diamondback/filters/polynomial_rate_filter.py
diamondback/filters/polyphase_rate_filter.py
diamondback/filters/rank_filter.py
diamondback/filters/window_filter.py
diamondback/models/__init__.py
diamondback/models/diversity_model.py
diamondback/models/gaussian_mixture_model.py
diamondback/models/gaussian_model.py
diamondback/transforms/__init__.py
diamondback/transforms/complex_transform.py
diamondback/transforms/fourier_transform.py
diamondback/transforms/psd_transform.py
diamondback/transforms/wavelet_transform.py
diamondback/transforms/z_transform.py
diamondback-5.2.0.dist-info/METADATA
diamondback-5.2.0.dist-info/WHEEL
diamondback-5.2.0.dist-info/top_level.txt
diamondback-5.2.0.dist-info/RECORD
