Metadata-Version: 2.4
Name: diamondback
Version: 5.2.0
Summary: Diamondback DSP
Author-email: Larry Turner <larry.turner@se.com>
License-Expression: BSD-3-Clause
Project-URL: homepage, https://github.com/larryturner/diamondback
Keywords: DSP,FFT,FIR,GMM,JSON,IIR,PSD
Classifier: Development Status :: 5 - Production/Stable
Classifier: Operating System :: OS Independent
Classifier: Programming Language :: Python :: 3.11
Classifier: Programming Language :: Python :: 3.12
Classifier: Programming Language :: Python :: 3.13
Classifier: Programming Language :: Python :: 3.14
Requires-Python: <3.15,>=3.11
Requires-Dist: jsonpickle<5.0.0,>=4.0.0
Requires-Dist: loguru<1.0.0,>=0.7.1
Requires-Dist: numpy<3.0.0,>=1.25.0
Requires-Dist: pandas<3.0.0,>=2.1.0
Requires-Dist: requests<3.0.0,>=2.31.0
Requires-Dist: scikit-learn<2.0.0,>=1.3.0
Requires-Dist: scipy<2.0.0,>=1.11.1
Provides-Extra: build
Requires-Dist: build<2.0.0,>=1.2.2; extra == "build"
Requires-Dist: virtualenv<21.0.0,>=20.29.3; extra == "build"
Provides-Extra: dependencies
Requires-Dist: pydeps<4.0.0,>=3.0.1; extra == "dependencies"
Provides-Extra: docs
Requires-Dist: sphinx<9.0.0,>=8.2.3; extra == "docs"
Requires-Dist: sphinx-rtd-theme<4.0.0,>=3.0.2; extra == "docs"
Provides-Extra: format
Requires-Dist: ruff<1.0.0,>=0.11.3; extra == "format"
Provides-Extra: lint
Requires-Dist: ruff<1.0.0,>=0.11.3; extra == "lint"
Provides-Extra: notebook
Requires-Dist: ipython<9.0.0,>=8.31.0; extra == "notebook"
Requires-Dist: ipywidgets<9.0.0,>=8.1.5; extra == "notebook"
Requires-Dist: jupyter<2.0.0,>=1.1.1; extra == "notebook"
Requires-Dist: matplotlib<4.0.0,>=3.10.1; extra == "notebook"
Requires-Dist: pillow<12.0.0,>=11.1.0; extra == "notebook"
Provides-Extra: tests
Requires-Dist: pytest<9.0.0,>=8.3.5; extra == "tests"
Provides-Extra: typing
Requires-Dist: mypy<2.0.0,>=1.15.0; extra == "typing"
Requires-Dist: types-python-dateutil<3.0.0,>=2.9.0; extra == "typing"
Requires-Dist: types-requests<3.0.0,>=2.31.0; extra == "typing"
